{
  "stock_id": "1337",
  "stock_name": "",
  "last_synced": "2026-01-30T00:30:54.452435",
  "source": "legacy_migration",
  "dividends": [
    {
      "date": "2018-01-01",
      "amount": 0.00289
    },
    {
      "date": "2017-01-01",
      "amount": 0.006996
    },
    {
      "date": "2016-01-01",
      "amount": 0.291503
    },
    {
      "date": "2015-01-01",
      "amount": 0.042754
    },
    {
      "date": "2014-01-01",
      "amount": 0.748336
    },
    {
      "date": "2013-01-01",
      "amount": 2.362707
    },
    {
      "date": "2012-01-01",
      "amount": 1.725888
    }
  ]
}