{
  "stock_id": "2426",
  "stock_name": "",
  "last_synced": "2026-01-30T00:30:54.391291",
  "source": "legacy_migration",
  "dividends": [
    {
      "date": "2025-01-01",
      "amount": 0.1
    },
    {
      "date": "2024-01-01",
      "amount": 0.2
    },
    {
      "date": "2022-01-01",
      "amount": 1.0
    },
    {
      "date": "2021-01-01",
      "amount": 0.75
    },
    {
      "date": "2020-01-01",
      "amount": 0.302674
    },
    {
      "date": "2019-01-01",
      "amount": 1.2
    },
    {
      "date": "2018-01-01",
      "amount": 0.699996
    },
    {
      "date": "2017-01-01",
      "amount": 0.72393
    },
    {
      "date": "2016-01-01",
      "amount": 1.0237
    },
    {
      "date": "2015-01-01",
      "amount": 0.9
    },
    {
      "date": "2011-01-01",
      "amount": 0.707013
    },
    {
      "date": "2010-01-01",
      "amount": 0.446828
    },
    {
      "date": "2008-01-01",
      "amount": 0.767935
    },
    {
      "date": "2007-01-01",
      "amount": 0.677098
    },
    {
      "date": "2006-01-01",
      "amount": 0.492776
    }
  ]
}