{
  "stock_id": "2834",
  "stock_name": "",
  "last_synced": "2026-01-30T00:30:54.341777",
  "source": "legacy_migration",
  "dividends": [
    {
      "date": "2025-01-01",
      "amount": 0.2
    },
    {
      "date": "2024-01-01",
      "amount": 0.188679
    },
    {
      "date": "2023-01-01",
      "amount": 0.08461
    },
    {
      "date": "2022-01-01",
      "amount": 0.082626
    },
    {
      "date": "2021-01-01",
      "amount": 0.079678
    },
    {
      "date": "2020-01-01",
      "amount": 0.154117
    },
    {
      "date": "2019-01-01",
      "amount": 0.209683
    },
    {
      "date": "2018-01-01",
      "amount": 0.187317
    },
    {
      "date": "2017-01-01",
      "amount": 0.066553
    },
    {
      "date": "2016-01-01",
      "amount": 0.062141
    }
  ]
}