{
  "stock_id": "6582",
  "stock_name": "",
  "last_synced": "2026-01-30T00:30:54.440835",
  "source": "legacy_migration",
  "dividends": [
    {
      "date": "2025-01-01",
      "amount": 1.0
    },
    {
      "date": "2023-01-01",
      "amount": 1.5
    },
    {
      "date": "2022-01-01",
      "amount": 15.0
    },
    {
      "date": "2021-01-01",
      "amount": 10.0
    },
    {
      "date": "2020-01-01",
      "amount": 4.449474
    },
    {
      "date": "2019-01-01",
      "amount": 3.59262
    },
    {
      "date": "2018-01-01",
      "amount": 3.48649
    },
    {
      "date": "2017-01-01",
      "amount": 3.619467
    },
    {
      "date": "2016-01-01",
      "amount": 4.0
    }
  ]
}