{"3561": {"cash": 0.0, "stock": 0.18211920529801473}, "2833": {"cash": 0.0, "stock": 0.3953646898432184}, "01005T": {"cash": 0.371, "stock": 0.0}, "01008T": {"cash": 0.415789, "stock": 0.0}, "2014": {"cash": 0.0, "stock": 0.29551954242135414}, "01004T": {"cash": 0.396704, "stock": 0.0}, "0052": {"cash": 1.461, "stock": 0.0}, "01001T": {"cash": 0.443381, "stock": 0.0}, "01003T": {"cash": 0.391188, "stock": 0.0}, "3622": {"cash": 5.47725, "stock": 1.369417593841935}, "2430": {"cash": 1.5, "stock": 0.0}, "01007T": {"cash": 0.417123, "stock": 0.0}, "01002T": {"cash": 0.479068, "stock": 0.0}, "2317": {"cash": 0.0, "stock": 0.0}, "1615": {"cash": 0.25, "stock": 0.0}, "2450": {"cash": 3.952448, "stock": 0.0}, "6139": {"cash": 2.5, "stock": 0.0}, "8070": {"cash": 2.0, "stock": 0.0}, "2345": {"cash": 0.661, "stock": 0.0}, "2548": {"cash": 4.908649, "stock": 0.0}, "4108": {"cash": 0.0, "stock": 0.3516105237275635}, "3296": {"cash": 1.0, "stock": 0.0}, "1716": {"cash": 1.5, "stock": 0.0}, "2038": {"cash": 2.0, "stock": 0.24208566108007368}, "2480": {"cash": 1.69, "stock": 0.0}, "2707": {"cash": 10.73, "stock": 1.000226808800182}, "3029": {"cash": 0.5025, "stock": 0.0}, "6281": {"cash": 3.2, "stock": 0.0}, "2464": {"cash": 2.1, "stock": 0.0}, "2538": {"cash": 0.6, "stock": 0.5028644175684271}, "3006": {"cash": 1.003568, "stock": 0.0}, "3058": {"cash": 0.78, "stock": 0.29934043632673824}, "8021": {"cash": 0.0, "stock": 0.20179372197309364}, "9924": {"cash": 0.7, "stock": 0.0}, "1710": {"cash": 1.0, "stock": 0.0}, "2360": {"cash": 0.0, "stock": 0.0}, "9910": {"cash": 1.2, "stock": 0.0}, "9931": {"cash": 0.3, "stock": 0.0}, "1717": {"cash": 1.5, "stock": 0.10293556995806252}, "9942": {"cash": 2.795988, "stock": 0.0}, "1451": {"cash": 0.5, "stock": 0.0}, "1733": {"cash": 0.0, "stock": 0.0}, "2340": {"cash": 0.249805, "stock": 0.0}, "2373": {"cash": 1.09, "stock": 0.0}, "2433": {"cash": 2.25, "stock": 0.0}, "6189": {"cash": 1.6, "stock": 0.0}, "1233": {"cash": 1.4, "stock": 0.0}, "1507": {"cash": 1.0, "stock": 0.0}, "1711": {"cash": 0.2, "stock": 0.0}, "2535": {"cash": 0.9, "stock": 0.0}, "6184": {"cash": 3.0, "stock": 0.0}, "8249": {"cash": 0.2, "stock": 0.0}, "1476": {"cash": 0.4, "stock": 0.2034709754637931}, "1773": {"cash": 1.5, "stock": 0.0}, "2338": {"cash": 0.65, "stock": 0.0}, "3090": {"cash": 2.2, "stock": 0.0}, "1513": {"cash": 0.88, "stock": 0.0}, "1560": {"cash": 1.2, "stock": 0.0}, "3045": {"cash": 4.68704, "stock": 0.0}, "1323": {"cash": 0.6, "stock": 0.0}, "1521": {"cash": 1.0, "stock": 0.0}, "1707": {"cash": 1.0, "stock": 0.0}, "1731": {"cash": 0.3, "stock": 0.0}, "2207": {"cash": 2.5, "stock": 0.0}, "2459": {"cash": 1.2, "stock": 0.0}, "2536": {"cash": 2.5, "stock": 0.0}, "2892": {"cash": 0.0, "stock": 0.0}, "3013": {"cash": 0.32, "stock": 0.0}, "3027": {"cash": 0.2, "stock": 0.0}, "3094": {"cash": 0.53798, "stock": 0.0}, "3356": {"cash": 10.0, "stock": 0.0}, "5388": {"cash": 1.49893, "stock": 0.0}, "6505": {"cash": 0.0, "stock": 0.0}, "9930": {"cash": 2.7, "stock": 0.0}, "1215": {"cash": 0.7, "stock": 0.0}, "1301": {"cash": 0.0, "stock": 0.0}, "2010": {"cash": 0.2, "stock": 0.3049907578558231}, "2015": {"cash": 2.0, "stock": 0.0}, "2107": {"cash": 0.5, "stock": 0.0}, "6164": {"cash": 0.85, "stock": 0.0}, "1315": {"cash": 1.0, "stock": 0.0}, "1477": {"cash": 2.001368, "stock": 0.0}, "2049": {"cash": 0.6, "stock": 0.0}, "2417": {"cash": 0.0, "stock": 0.0}, "2423": {"cash": 1.0, "stock": 0.0}, "2439": {"cash": 2.62, "stock": 0.0}, "2901": {"cash": 0.27895, "stock": 0.0}, "3130": {"cash": 4.23, "stock": 0.0}, "5305": {"cash": 0.6, "stock": 0.0}, "6136": {"cash": 0.0, "stock": 0.0}, "6155": {"cash": 1.5, "stock": 0.10285335102853344}, "8072": {"cash": 6.0, "stock": 0.0}, "8940": {"cash": 0.0, "stock": 0.0}, "9907": {"cash": 0.65, "stock": 0.0}, "1723": {"cash": 4.65, "stock": 0.0}, "2404": {"cash": 0.97, "stock": 0.0}, "2325": {"cash": 1.8, "stock": 0.0}, "3443": {"cash": 0.0, "stock": 0.0}, "6112": {"cash": 1.2, "stock": 0.0}, "1612": {"cash": 0.26, "stock": 0.0}, "2029": {"cash": 1.5, "stock": 0.0}, "2308": {"cash": 0.0, "stock": 0.0}, "2327": {"cash": 0.1, "stock": 0.0}, "2351": {"cash": 0.3, "stock": 0.0}, "2420": {"cash": 0.8, "stock": 0.0}, "2493": {"cash": 0.25, "stock": 0.0}, "3450": {"cash": 0.5, "stock": 0.0}, "3545": {"cash": 1.182503, "stock": 0.0}, "6192": {"cash": 1.5, "stock": 1.0009910802775024}, "8033": {"cash": 0.2, "stock": 0.0}, "9943": {"cash": 1.0, "stock": 0.0}, "1232": {"cash": 2.4, "stock": 0.0}, "1234": {"cash": 0.3, "stock": 0.0}, "1465": {"cash": 0.55, "stock": 0.0}, "1535": {"cash": 2.0, "stock": 0.0}, "2314": {"cash": 0.0, "stock": 0.0}, "2328": {"cash": 0.0, "stock": 0.0}, "2330": {"cash": 0.0, "stock": 0.0}, "2356": {"cash": 0.0, "stock": 0.0}, "2419": {"cash": 0.0, "stock": 0.0}, "2504": {"cash": 0.0, "stock": 0.3125}, "3033": {"cash": 0.910153, "stock": 0.0}, "3044": {"cash": 0.0, "stock": 0.0}, "3080": {"cash": 1.0, "stock": 0.0}, "3189": {"cash": 2.0, "stock": 0.0}, "3315": {"cash": 2.5, "stock": 0.0}, "3367": {"cash": 0.0, "stock": 0.0}, "3532": {"cash": 0.0, "stock": 0.0}, "6257": {"cash": 0.5, "stock": 0.0}, "8163": {"cash": 0.0, "stock": 0.0}, "8201": {"cash": 0.0, "stock": 0.0}, "1109": {"cash": 0.2, "stock": 0.0}, "1303": {"cash": 0.0, "stock": 0.0}, "1445": {"cash": 0.208465, "stock": 0.0}, "1454": {"cash": 0.2, "stock": 0.0}, "1525": {"cash": 0.0, "stock": 0.0}, "1540": {"cash": 1.5, "stock": 1.5037593984962405}, "1614": {"cash": 0.317501, "stock": 0.0}, "1713": {"cash": 0.1, "stock": 0.0}, "1727": {"cash": 0.2, "stock": 0.6060606060606055}, "2013": {"cash": 0.9, "stock": 0.0}, "2468": {"cash": 0.7, "stock": 0.0}, "2526": {"cash": 0.35, "stock": 0.0}, "2612": {"cash": 6.8, "stock": 0.0}, "2891": {"cash": 0.18, "stock": 0.32122169562928127}, "3015": {"cash": 0.0, "stock": 0.0}, "3023": {"cash": 1.1, "stock": 0.0}, "3061": {"cash": 0.11254, "stock": 0.0}, "3702": {"cash": 1.398795, "stock": 0.0}, "4106": {"cash": 0.0, "stock": 0.0}, "6215": {"cash": 0.75004, "stock": 0.0}, "8926": {"cash": 1.2, "stock": 0.0}, "9908": {"cash": 0.8, "stock": 0.0}, "9917": {"cash": 3.0, "stock": 0.0}, "2012": {"cash": 0.6, "stock": 0.0}, "2108": {"cash": 0.8, "stock": 0.804450149764655}, "2315": {"cash": 0.2, "stock": 0.0}, "2454": {"cash": 0.0, "stock": 0.0}, "2457": {"cash": 0.78299, "stock": 0.0}, "6216": {"cash": 1.595686, "stock": 0.0}, "6283": {"cash": 0.0, "stock": 0.5081826012058577}, "8131": {"cash": 1.0, "stock": 0.0}, "9918": {"cash": 1.0, "stock": 0.0}, "1434": {"cash": 1.5, "stock": 0.0}, "1503": {"cash": 0.6, "stock": 0.0}, "1701": {"cash": 0.2, "stock": 0.0}, "1720": {"cash": 0.0, "stock": 0.0}, "2353": {"cash": 0.0, "stock": 0.0}, "2449": {"cash": 0.0, "stock": 0.0}, "2606": {"cash": 6.0, "stock": 0.0}, "3002": {"cash": 1.0, "stock": 0.0}, "3060": {"cash": 0.0, "stock": 0.0}, "3504": {"cash": 3.3, "stock": 0.0}, "6141": {"cash": 1.080011, "stock": 0.0}, "6166": {"cash": 0.0, "stock": 0.0}, "6205": {"cash": 0.8, "stock": 0.0}, "9905": {"cash": 0.9, "stock": 0.0}, "9919": {"cash": 0.0, "stock": 0.0}, "1236": {"cash": 1.0, "stock": 0.0}, "2350": {"cash": 0.319848, "stock": 0.0}, "2362": {"cash": 0.0, "stock": 0.5049396267837558}, "2461": {"cash": 0.2, "stock": 0.0}, "3535": {"cash": 0.0, "stock": 0.0}, "5484": {"cash": 0.0, "stock": 0.0}, "3019": {"cash": 0.0, "stock": 0.0}, "1308": {"cash": 1.0, "stock": 0.0}, "1326": {"cash": 0.0, "stock": 0.0}, "2365": {"cash": 0.0, "stock": 0.0}, "2421": {"cash": 0.0, "stock": 0.0}, "2437": {"cash": 0.0, "stock": 0.0}, "2483": {"cash": 0.3085, "stock": 0.0}, "2509": {"cash": 1.497904, "stock": 0.0}, "2801": {"cash": 0.6, "stock": 0.0}, "2910": {"cash": 1.0, "stock": 0.0}, "4904": {"cash": 2.8, "stock": 0.0}, "6286": {"cash": 0.0, "stock": 0.0}, "8081": {"cash": 0.0, "stock": 0.0}, "9937": {"cash": 1.0, "stock": 0.0}, "9941": {"cash": 1.7, "stock": 0.0}, "1611": {"cash": 0.6, "stock": 0.0}, "2002": {"cash": 0.0, "stock": 0.0}, "2002A": {"cash": 0.0, "stock": 0.0}, "2201": {"cash": 0.079998, "stock": 0.0}, "4526": {"cash": 0.0, "stock": 0.0}, "5533": {"cash": 0.0, "stock": 0.0}, "2311": {"cash": 0.499891, "stock": 0.0}, "2527": {"cash": 0.3, "stock": 0.0}, "6176": {"cash": 0.0, "stock": 0.0}, "1734": {"cash": 0.330159, "stock": 0.0}, "2103": {"cash": 2.8, "stock": 0.0}, "2354": {"cash": 0.0, "stock": 0.0}, "2374": {"cash": 0.0, "stock": 0.0}, "2380": {"cash": 0.2988, "stock": 0.0}, "2383": {"cash": 0.0, "stock": 0.0}, "2385": {"cash": 0.0, "stock": 0.0}, "2392": {"cash": 0.0, "stock": 0.0}, "3533": {"cash": 1.8, "stock": 0.0}, "4725": {"cash": 0.31, "stock": 0.0}, "5608": {"cash": 0.0, "stock": 0.0}, "9925": {"cash": 1.0, "stock": 0.0}, "9944": {"cash": 0.2, "stock": 0.0}, "1704": {"cash": 1.25, "stock": 0.7530032229709938}, "2395": {"cash": 0.0, "stock": 0.0}, "2542": {"cash": 0.0, "stock": 0.0}, "3022": {"cash": 0.0, "stock": 0.0}, "3376": {"cash": 0.0, "stock": 0.0}, "6277": {"cash": 0.0, "stock": 0.0}, "1473": {"cash": 0.0, "stock": 0.0}, "2031": {"cash": 0.0, "stock": 0.0}, "2106": {"cash": 0.0, "stock": 0.0}, "2382": {"cash": 0.0, "stock": 0.0}, "2448": {"cash": 0.119952, "stock": 0.0}, "2488": {"cash": 1.0, "stock": 0.0}, "2820": {"cash": 0.89, "stock": 0.0}, "2886": {"cash": 0.25, "stock": 0.0}, "3010": {"cash": 0.0, "stock": 0.0}, "3037": {"cash": 0.7, "stock": 0.0}, "3515": {"cash": 0.0, "stock": 0.0}, "6108": {"cash": 0.926994, "stock": 0.0}, "6226": {"cash": 0.0, "stock": 0.3684971098265888}, "6269": {"cash": 0.0, "stock": 0.0}, "1313": {"cash": 0.196863, "stock": 0.0}, "1808": {"cash": 0.0, "stock": 0.0}, "2415": {"cash": 0.25, "stock": 0.0}, "3576": {"cash": 0.0, "stock": 0.0}, "4906": {"cash": 0.0, "stock": 0.0}, "6202": {"cash": 0.0, "stock": 0.0}, "1227": {"cash": 0.0, "stock": 0.0}, "2412": {"cash": 0.0, "stock": 0.0}, "2452": {"cash": 0.0, "stock": 0.0}, "2467": {"cash": 0.0, "stock": 0.0}, "2476": {"cash": 0.0, "stock": 0.0}, "2481": {"cash": 0.4, "stock": 0.0}, "2498": {"cash": 0.0, "stock": 0.0}, "1325": {"cash": 0.0, "stock": 0.0}, "1726": {"cash": 1.8, "stock": 0.0}, "2105": {"cash": 0.0, "stock": 0.0}, "2477": {"cash": 0.25, "stock": 0.0}, "3025": {"cash": 0.35242, "stock": 0.0}, "3231": {"cash": 0.0, "stock": 0.0}, "3308": {"cash": 1.199291, "stock": 0.0}, "5469": {"cash": 0.7939, "stock": 0.0}, "5471": {"cash": 2.99, "stock": 0.0}, "6131": {"cash": 1.0, "stock": 0.0}, "6201": {"cash": 2.0, "stock": 0.0}, "6213": {"cash": 1.0293, "stock": 0.0}, "9904": {"cash": 0.0, "stock": 0.0}, "1307": {"cash": 0.0, "stock": 0.0}, "2033": {"cash": 0.0, "stock": 0.0}, "2355": {"cash": 0.0, "stock": 0.0}, "2520": {"cash": 0.5, "stock": 0.0}, "2546": {"cash": 0.5, "stock": 0.0}, "2616": {"cash": 0.5041, "stock": 0.0}, "2904": {"cash": 0.5, "stock": 0.0}, "3034": {"cash": 0.0, "stock": 0.0}, "3209": {"cash": 0.0, "stock": 0.0}, "5434": {"cash": 0.0, "stock": 0.0}, "1712": {"cash": 0.0, "stock": 0.0}, "2377": {"cash": 0.0, "stock": 0.0}, "2403": {"cash": 0.0, "stock": 0.0}, "2428": {"cash": 1.05, "stock": 0.0}, "2463": {"cash": 0.0, "stock": 0.0}, "2485": {"cash": 3.0, "stock": 0.0}, "2903": {"cash": 0.0, "stock": 0.0}, "3028": {"cash": 0.799534, "stock": 0.0}, "3035": {"cash": 0.0, "stock": 0.0}, "3380": {"cash": 0.0, "stock": 0.0}, "4119": {"cash": 0.0, "stock": 0.0}, "5515": {"cash": 0.0, "stock": 0.0}, "6117": {"cash": 0.5, "stock": 0.0}, "6128": {"cash": 0.0, "stock": 0.0}, "6239": {"cash": 0.0, "stock": 0.0}, "9921": {"cash": 0.0, "stock": 0.0}, "9940": {"cash": 1.794285, "stock": 0.0}, "9945": {"cash": 0.4, "stock": 0.0}, "1229": {"cash": 0.0, "stock": 0.0}, "2545": {"cash": 0.0, "stock": 1.5012106537530268}, "3008": {"cash": 0.0, "stock": 0.0}, "3047": {"cash": 0.0, "stock": 0.0}, "3057": {"cash": 0.0, "stock": 0.0}, "9939": {"cash": 0.0, "stock": 0.0}, "1802": {"cash": 0.0, "stock": 0.0}, "2458": {"cash": 0.0, "stock": 0.0}, "2473": {"cash": 0.8, "stock": 0.0}, "2617": {"cash": 4.25, "stock": 0.0}, "3005": {"cash": 0.9929, "stock": 0.0}, "3055": {"cash": 0.0, "stock": 0.0}, "3305": {"cash": 0.0, "stock": 0.0}, "3614": {"cash": 0.0, "stock": 0.0}, "5531": {"cash": 0.0, "stock": 1.0012360939431408}, "6115": {"cash": 0.0, "stock": 0.0}, "6282": {"cash": 0.0, "stock": 0.0}, "1583": {"cash": 0.0, "stock": 0.0}, "2601": {"cash": 0.0, "stock": 0.0}, "3003": {"cash": 0.0, "stock": 0.0}, "3501": {"cash": 0.0, "stock": 0.0}, "1210": {"cash": 0.0, "stock": 0.0}, "1530": {"cash": 0.0, "stock": 0.0}, "2006": {"cash": 0.0, "stock": 0.0}, "2347": {"cash": 0.0, "stock": 0.0}, "2409": {"cash": 0.0, "stock": 0.0}, "2547": {"cash": 0.0, "stock": 0.4828773390230401}, "2880": {"cash": 0.0, "stock": 0.0}, "2908": {"cash": 0.0, "stock": 0.0}, "2912": {"cash": 0.0, "stock": 0.0}, "4306": {"cash": 0.0, "stock": 0.0}, "8374": {"cash": 0.0, "stock": 0.0}, "1722": {"cash": 1.8, "stock": 0.0}, "2397": {"cash": 0.0, "stock": 0.0}, "2884": {"cash": 0.0, "stock": 0.30927835051546504}, "2885": {"cash": 0.18, "stock": 0.0}, "2911": {"cash": 0.0, "stock": 0.0}, "3311": {"cash": 0.0, "stock": 0.0}, "6271": {"cash": 0.0, "stock": 0.0}, "8008": {"cash": 0.0, "stock": 0.0}, "8016": {"cash": 0.0, "stock": 0.0}, "2104": {"cash": 1.5, "stock": 0.29623238423928555}, "2841": {"cash": 0.0, "stock": 0.7954460513529926}, "3031": {"cash": 0.0, "stock": 0.0}, "3481": {"cash": 0.0, "stock": 0.0}, "3514": {"cash": 0.0, "stock": 4.369151753738645}, "1101": {"cash": 1.32, "stock": 0.0}, "1452": {"cash": 0.0, "stock": 0.20689655172413834}, "2301": {"cash": 0.0, "stock": 0.0}, "2460": {"cash": 0.0, "stock": 0.0}, "3041": {"cash": 0.0, "stock": 0.0}, "9105": {"cash": 0.0482, "stock": 0.0}, "9926": {"cash": 0.0, "stock": 0.0}, "1216": {"cash": 0.0, "stock": 0.0}, "1231": {"cash": 0.7, "stock": 0.0}, "2324": {"cash": 0.0, "stock": 0.0}, "2357": {"cash": 0.0, "stock": 0.0}, "2426": {"cash": 0.0, "stock": 0.6451397489133326}, "2484": {"cash": 0.0, "stock": 0.0}, "2534": {"cash": 1.0, "stock": 0.0}, "5854": {"cash": 0.8, "stock": 0.0}, "2478": {"cash": 0.0, "stock": 0.0}, "2605": {"cash": 2.5, "stock": 0.0}, "6142": {"cash": 0.0, "stock": 0.0}, "6191": {"cash": 0.0, "stock": 1.0027855153203347}, "2376": {"cash": 1.0, "stock": 0.0}, "2486": {"cash": 0.0, "stock": 0.0}, "3026": {"cash": 0.0, "stock": 0.0}, "4104": {"cash": 1.933009, "stock": 0.0}, "6168": {"cash": 0.0, "stock": 0.0}, "6206": {"cash": 4.0, "stock": 0.0}, "9955": {"cash": 1.3, "stock": 0.0}, "2332": {"cash": 0.0, "stock": 0.0}, "2489": {"cash": 0.0, "stock": 0.0}, "3024": {"cash": 0.0, "stock": 0.3238866396761142}, "3494": {"cash": 0.0, "stock": 0.0}, "5534": {"cash": 0.0, "stock": 0.0}, "9933": {"cash": 1.919228, "stock": 0.0}, "1102": {"cash": 0.0, "stock": 0.0}, "1319": {"cash": 0.0, "stock": 0.0}, "2379": {"cash": 0.0, "stock": 0.0}, "3042": {"cash": 0.0, "stock": 0.0}, "3383": {"cash": 0.0, "stock": 0.0}, "6251": {"cash": 2.0, "stock": 0.0}, "1402": {"cash": 0.0, "stock": 0.0}, "1523": {"cash": 0.0, "stock": 0.0}, "1709": {"cash": 0.0, "stock": 0.0}, "2020": {"cash": 0.0, "stock": 1.0000000000000009}, "2062": {"cash": 1.1, "stock": 0.0}, "2387": {"cash": 1.209855, "stock": 0.0}, "2441": {"cash": 0.0, "stock": 0.0}, "2495": {"cash": 0.0, "stock": 0.0}, "2609": {"cash": 0.15, "stock": 0.0}, "3559": {"cash": 0.999627, "stock": 0.0}, "1504": {"cash": 0.5, "stock": 0.0}, "2059": {"cash": 0.0, "stock": 0.0}, "2337": {"cash": 0.0, "stock": 0.0}, "2702": {"cash": 0.0, "stock": 0.35196687370600444}, "3534": {"cash": 0.0, "stock": 0.0}, "5522": {"cash": 2.5, "stock": 0.0}, "8046": {"cash": 0.0, "stock": 0.0}, "1528": {"cash": 0.0, "stock": 0.0}, "2456": {"cash": 0.3, "stock": 0.0}, "3059": {"cash": 0.0, "stock": 0.0}, "3518": {"cash": 2.996033, "stock": 0.0}, "9934": {"cash": 0.5, "stock": 0.0}, "3014": {"cash": 0.999786, "stock": 0.0}, "9911": {"cash": 0.0, "stock": 0.0}, "1538": {"cash": 0.0, "stock": 0.0}, "9914": {"cash": 0.0, "stock": 0.0}, "2023": {"cash": 0.0, "stock": 0.0}, "2391": {"cash": 0.308725, "stock": 0.0}, "3605": {"cash": 0.0, "stock": 0.0}, "1730": {"cash": 0.5, "stock": 0.0}, "1905": {"cash": 0.15, "stock": 0.0}, "1524": {"cash": 0.0, "stock": 0.0}, "2208": {"cash": 0.0, "stock": 0.0}, "2451": {"cash": 0.0, "stock": 0.0}, "2608": {"cash": 0.512355, "stock": 0.0}, "2704": {"cash": 0.5, "stock": 0.0}, "3036": {"cash": 0.0, "stock": 0.0}, "9151": {"cash": 0.1971, "stock": 0.0}, "3017": {"cash": 0.0, "stock": 0.0}, "9938": {"cash": 0.5, "stock": 0.0}, "1522": {"cash": 0.0, "stock": 0.0}, "3062": {"cash": 0.0, "stock": 0.0}, "6285": {"cash": 0.0, "stock": 0.0}, "1729": {"cash": 0.999749, "stock": 0.0}, "2462": {"cash": 0.0, "stock": 0.0}, "5203": {"cash": 0.0, "stock": 0.0}, "2034": {"cash": 0.0, "stock": 0.0}, "2369": {"cash": 0.0, "stock": 0.0}, "2474": {"cash": 0.0, "stock": 0.0}, "5525": {"cash": 0.0, "stock": 0.0}, "1517": {"cash": 0.7, "stock": 0.0}, "1736": {"cash": 0.0, "stock": 0.0}, "2515": {"cash": 0.12, "stock": 0.0}, "3593": {"cash": 0.0, "stock": 0.0}, "1519": {"cash": 0.0, "stock": 0.0}, "1531": {"cash": 0.7, "stock": 0.0}, "1708": {"cash": 1.5, "stock": 0.0}, "2611": {"cash": 0.0, "stock": 0.5022831050228316}, "6119": {"cash": 0.0, "stock": 0.0}, "6196": {"cash": 0.0, "stock": 1.0047846889952172}, "8078": {"cash": 1.2, "stock": 0.0}, "1324": {"cash": 0.1, "stock": 0.0}, "1442": {"cash": 1.2, "stock": 0.0}, "1724": {"cash": 0.0, "stock": 0.0}, "2706": {"cash": 0.0, "stock": 0.0}, "2812": {"cash": 0.105, "stock": 0.0}, "3030": {"cash": 0.0, "stock": 0.0}, "3040": {"cash": 0.310956, "stock": 0.0}, "6133": {"cash": 0.3, "stock": 0.0}, "1203": {"cash": 0.0, "stock": 0.0}, "1714": {"cash": 0.0, "stock": 0.5519480519480524}, "2331": {"cash": 0.25, "stock": 0.0}, "2414": {"cash": 1.375, "stock": 0.0}, "3519": {"cash": 0.0, "stock": 0.0}, "6605": {"cash": 3.6, "stock": 0.0}, "1537": {"cash": 0.36, "stock": 0.0}, "2393": {"cash": 3.19761, "stock": 0.06959547629404206}, "2701": {"cash": 0.0, "stock": 0.0}, "3596": {"cash": 0.0, "stock": 0.08279914529914612}, "9104": {"cash": 0.42, "stock": 0.0}, "1806": {"cash": 0.0, "stock": 0.08245877061469287}, "1235": {"cash": 0.0, "stock": 0.30158256195879307}, "1527": {"cash": 1.229875, "stock": 0.0}, "3049": {"cash": 0.0, "stock": 1.2187679907887161}, "9958": {"cash": 0.0, "stock": 0.21775544388609624}, "9188": {"cash": 0.15, "stock": 0.0}, "1618": {"cash": 0.0, "stock": 0.2008928571428581}, "0050": {"cash": 1.0, "stock": 0.0}, "0056": {"cash": 2.0, "stock": 0.0}, "1532": {"cash": 0.0, "stock": 0.0}, "2888": {"cash": 0.0, "stock": 0.16582552271088735}, "2349": {"cash": 0.0, "stock": 0.16861219195849486}, "1471": {"cash": 0.0, "stock": 0.2564102564102555}, "1909": {"cash": 0.0, "stock": 0.17029328287606393}, "2388": {"cash": 0.0, "stock": 0.667340748230536}, "2823": {"cash": 0.0, "stock": 0.24432061723103304}, "2368": {"cash": 0.0, "stock": 0.0}, "2408": {"cash": 0.0, "stock": 0.6066693451185201}, "0051": {"cash": 1.7, "stock": 0.0}, "2455": {"cash": 0.0, "stock": 0.19074993467467882}, "0080": {"cash": 1.48428, "stock": 0.0}, "0081": {"cash": 8.246, "stock": 0.0}}